Hedwig/__init__.py
Hedwig/__main__.py
Hedwig/cli.py
Hedwig/health.py
Hedwig/llm.py
Hedwig/pipeline.py
Hedwig/change_summary/__init__.py
Hedwig/change_summary/diff_analyzer.py
Hedwig/change_summary/generator.py
Hedwig/messaging/__init__.py
Hedwig/messaging/base.py
Hedwig/messaging/factory.py
Hedwig/messaging/manager.py
Hedwig/messaging/consumers/__init__.py
Hedwig/messaging/consumers/slack.py
Hedwig/notion/__init__.py
Hedwig/notion/client.py
Hedwig/notion/exporter.py
Hedwig/notion/sync.py
Hedwig/overview/__init__.py
Hedwig/overview/generator.py
Hedwig/utils/__init__.py
Hedwig/utils/config.py
Hedwig/utils/git.py
Hedwig/utils/logging.py
Hedwig/utils/markdown_converter.py
hedwiglab-0.9.0.dist-info/licenses/LICENSE.txt
hedwiglab-0.9.0.dist-info/METADATA
hedwiglab-0.9.0.dist-info/WHEEL
hedwiglab-0.9.0.dist-info/entry_points.txt
hedwiglab-0.9.0.dist-info/top_level.txt
hedwiglab-0.9.0.dist-info/RECORD
