Metadata-Version: 2.4
Name: HedwigLab
Version: 0.9.0
Summary: Research note backup storage that syncs Notion to Git and generates AI summaries
Author: Hyeshik Chang
Author-email: Hyeshik Chang <hyeshik@snu.ac.kr>
Classifier: Development Status :: 4 - Beta
Classifier: Intended Audience :: Science/Research
Classifier: Topic :: Scientific/Engineering :: Information Analysis
Classifier: Topic :: Office/Business
Classifier: Topic :: Text Processing :: Markup
Classifier: License :: OSI Approved :: MIT License
Classifier: Programming Language :: Python :: 3
Classifier: Programming Language :: Python :: 3.9
Classifier: Programming Language :: Python :: 3.10
Classifier: Programming Language :: Python :: 3.11
Classifier: Programming Language :: Python :: 3.12
Requires-Python: >=3.9
License-File: LICENSE.txt
Requires-Dist: click
Requires-Dist: requests
Requires-Dist: pandas
Requires-Dist: pytz
Requires-Dist: python-dateutil
Requires-Dist: pyyaml
Requires-Dist: notion-client
Requires-Dist: notion2md
Requires-Dist: tqdm
Requires-Dist: openai
Requires-Dist: tiktoken
Requires-Dist: python-dotenv
Requires-Dist: slack-sdk
Dynamic: author
Dynamic: license-file
Dynamic: requires-python
